aws_connections/CONFIG.json
aws_connections/Client.py
aws_connections/Connection.py
aws_connections/__init__.py
aws_connections/__main__.py
aws_connections/s3/__init__.py
aws_connections/s3/s3_dir_ops.py
kabbes_aws_connections-0.8.0.dist-info/LICENSE
kabbes_aws_connections-0.8.0.dist-info/METADATA
kabbes_aws_connections-0.8.0.dist-info/WHEEL
kabbes_aws_connections-0.8.0.dist-info/top_level.txt
kabbes_aws_connections-0.8.0.dist-info/RECORD
